ansys/motorcad/core/__init__.py
ansys/motorcad/core/datastore.py
ansys/motorcad/core/geometry.py
ansys/motorcad/core/geometry_drawing.py
ansys/motorcad/core/geometry_ellipse.py
ansys/motorcad/core/geometry_extrusion.py
ansys/motorcad/core/geometry_fitting.py
ansys/motorcad/core/geometry_shapes.py
ansys/motorcad/core/geometry_tree.py
ansys/motorcad/core/motorcad_methods.py
ansys/motorcad/core/rpc_client_core.py
ansys/motorcad/core/rpc_methods_core.py
ansys/motorcad/core/rpc_methods_core_old.py
ansys/motorcad/core/methods/__init__.py
ansys/motorcad/core/methods/adaptive_geometry.py
ansys/motorcad/core/methods/rpc_methods_calculations.py
ansys/motorcad/core/methods/rpc_methods_fea_geometry.py
ansys/motorcad/core/methods/rpc_methods_general.py
ansys/motorcad/core/methods/rpc_methods_geometry.py
ansys/motorcad/core/methods/rpc_methods_graphs.py
ansys/motorcad/core/methods/rpc_methods_internal.py
ansys/motorcad/core/methods/rpc_methods_internal_scripting.py
ansys/motorcad/core/methods/rpc_methods_lab.py
ansys/motorcad/core/methods/rpc_methods_materials.py
ansys/motorcad/core/methods/rpc_methods_testing.py
ansys/motorcad/core/methods/rpc_methods_thermal.py
ansys/motorcad/core/methods/rpc_methods_ui.py
ansys/motorcad/core/methods/rpc_methods_utility.py
ansys/motorcad/core/methods/rpc_methods_variables.py
ansys_motorcad_core-0.8.1.dist-info/licenses/LICENSE
ansys_motorcad_core-0.8.1.dist-info/WHEEL
ansys_motorcad_core-0.8.1.dist-info/METADATA
ansys_motorcad_core-0.8.1.dist-info/RECORD
