Metadata-Version: 2.4
Name: ansys-motorcad-core
Version: 0.8.1
Summary: Pythonic interface to Ansys Motor-CAD.
Author-email: "ANSYS, Inc." <pyansys.core@ansys.com>
Maintainer-email: "ANSYS, Inc." <pyansys.core@ansys.com>
Requires-Python: >=3.9
Classifier: Development Status :: 3 - Alpha
Classifier: Intended Audience :: Science/Research
Classifier: Topic :: Scientific/Engineering :: Physics
Classifier: License :: OSI Approved :: MIT License
Classifier: Operating System :: Microsoft :: Windows
Classifier: Programming Language :: Python :: 3.9
Classifier: Programming Language :: Python :: 3.10
Classifier: Programming Language :: Python :: 3.11
Classifier: Programming Language :: Python :: 3.12
Classifier: Programming Language :: Python :: 3.13
Classifier: Programming Language :: Python :: 3.14
License-File: LICENSE
Requires-Dist: psutil >= 5.9.0
Requires-Dist: requests >= 2.27.1
Requires-Dist: packaging >= 21.3
Requires-Dist: importlib-metadata>=4.0
Requires-Dist: openpyxl >=3.1.5
Requires-Dist: Sphinx==8.1.3 ; extra == "doc"
Requires-Dist: numpydoc==1.9.0 ; extra == "doc"
Requires-Dist: ansys-sphinx-theme==1.3.3 ; extra == "doc"
Requires-Dist: sphinx-copybutton==0.5.2 ; extra == "doc"
Requires-Dist: sphinx-gallery==0.19.0 ; extra == "doc"
Requires-Dist: matplotlib ; extra == "doc"
Requires-Dist: scipy ; extra == "doc"
Requires-Dist: pypandoc==1.15 ; extra == "doc"
Requires-Dist: networkx ; extra == "doc"
Requires-Dist: pytest==8.4.2 ; extra == "tests"
Requires-Dist: pytest-cov==7.0.0 ; extra == "tests"
Requires-Dist: ansys.platform.instancemanagement>=1.0.2 ; extra == "tests"
Requires-Dist: matplotlib>=3.6.3 ; extra == "tests"
Requires-Dist: scipy ; extra == "tests"
Project-URL: Documentation, https://motorcad.docs.pyansys.com/
Project-URL: Source, https://github.com/ansys/pymotorcad
Project-URL: Tracker, https://github.com/ansys/pymotorcad/issues
Provides-Extra: doc
Provides-Extra: tests
